{"version":1,"resource":"file:///Users/shiyun/workspace/sirius_FE/src/pages/desktop/Company/Detail/Graphs/components/riskGraph/riskGraph.store.ts","entries":[{"id":"Y8fN.ts","timestamp":1684372291418},{"id":"eTAp.ts","source":"undoRedo.source","timestamp":1684372305330},{"id":"iAfP.ts","timestamp":1684372312577},{"id":"o2Xw.ts","timestamp":1684372333907},{"id":"yy8H.ts","timestamp":1684462758431},{"id":"GJHv.ts","timestamp":1684462778198},{"id":"ROgg.ts","timestamp":1684479121642},{"id":"4a4Q.ts","timestamp":1685589405861},{"id":"nUh1.ts","timestamp":1685589438910},{"id":"yTxl.ts","timestamp":1685607894148},{"id":"O6To.ts","source":"undoRedo.source","timestamp":1685607938195}]}