{"version":1,"resource":"file:///Users/shiyun/workspace/bond_trade/src/main.ts","entries":[{"id":"KYcx.ts","timestamp":1649211635209},{"id":"XY5i.ts","timestamp":1649211655376},{"id":"3V15.ts","timestamp":1649215675826},{"id":"eumT.ts","timestamp":1649831391691},{"id":"UHOZ.ts","timestamp":1649831407479},{"id":"CPyL.ts","timestamp":1649831444759},{"id":"LdA9.ts","timestamp":1649831480991},{"id":"sHEs.ts","timestamp":1649832308190},{"id":"KViR.ts","timestamp":1649832321169},{"id":"SIMh.ts","timestamp":1649832410891},{"id":"iRrs.ts","timestamp":1649833902509},{"id":"EZAZ.ts","timestamp":1650253281186}]}