{"version":1,"resource":"file:///Users/shiyun/workspace/basic_framework/src/pages/Performance/Detail/Kpi.tsx","entries":[{"id":"p2Fg.tsx","source":"searchReplace.source","timestamp":1667297579879},{"id":"daWd.tsx","timestamp":1667469620918},{"id":"oAZc.tsx","timestamp":1667523711757},{"id":"TJGe.tsx","timestamp":1667523726343},{"id":"H5Bk.tsx","timestamp":1667523737472},{"id":"mYEA.tsx","timestamp":1667523762419},{"id":"d4uj.tsx","timestamp":1667523791653},{"id":"DQtU.tsx","timestamp":1667524172664},{"id":"Kav9.tsx","timestamp":1667524249861},{"id":"GBIx.tsx","timestamp":1667524282744},{"id":"QdjW.tsx","timestamp":1667524322581},{"id":"nuJN.tsx","source":"undoRedo.source","timestamp":1667524324177},{"id":"VZ8E.tsx","timestamp":1667524364509},{"id":"4vzX.tsx","timestamp":1667524500539},{"id":"0HqM.tsx","timestamp":1667524526523},{"id":"qLpe.tsx","source":"undoRedo.source","timestamp":1667524569808},{"id":"2z0t.tsx","timestamp":1667524584778},{"id":"D9vo.tsx","timestamp":1667524645249},{"id":"lffR.tsx","timestamp":1667524680778},{"id":"lqKr.tsx","timestamp":1667524705172},{"id":"kJeX.tsx","timestamp":1667524756677},{"id":"ijjz.tsx","timestamp":1667552036450},{"id":"2nMR.tsx","timestamp":1667552087990},{"id":"gQdv.tsx","timestamp":1667554140383},{"id":"9Lsi.tsx","timestamp":1667615403780},{"id":"7GNL.tsx","timestamp":1667615430316},{"id":"oJ6s.tsx","timestamp":1667615450295},{"id":"IHSR.tsx","timestamp":1667615525637},{"id":"6Hvz.tsx","timestamp":1667615550209},{"id":"FGic.tsx","timestamp":1667615573285},{"id":"Yalt.tsx","timestamp":1667615589410},{"id":"4C2g.tsx","timestamp":1667615648157},{"id":"JixY.tsx","timestamp":1667615680127},{"id":"v3Z8.tsx","timestamp":1667615719982},{"id":"45Kd.tsx","timestamp":1667615795502},{"id":"HlTu.tsx","timestamp":1667615945759},{"id":"M2t4.tsx","timestamp":1667616009224},{"id":"cavD.tsx","timestamp":1667617089556},{"id":"wmk5.tsx","timestamp":1670314281986},{"id":"Wes1.tsx","timestamp":1670314520104},{"id":"8kaS.tsx","timestamp":1670314558293},{"id":"WOnm.tsx","source":"undoRedo.source","timestamp":1670314563745},{"id":"Lsp4.tsx","timestamp":1670314570793},{"id":"1c8i.tsx","timestamp":1670314591198},{"id":"K2Vz.tsx","timestamp":1670314646854}]}