{"version":1,"resource":"file:///Users/shiyun/workspace/bond_trade/src/router/routes.ts","entries":[{"id":"poHC.ts","timestamp":1649751756080},{"id":"Na5J.ts","timestamp":1649751767085},{"id":"hkh8.ts","timestamp":1649751809140},{"id":"v9Lu.ts","timestamp":1649751820385},{"id":"HILn.ts","timestamp":1649751838135},{"id":"MiN4.ts","timestamp":1649751991952},{"id":"RCSo.ts","source":"undoRedo.source","timestamp":1649751995421},{"id":"yLss.ts","timestamp":1649752013377},{"id":"1Drb.ts","timestamp":1649752044738},{"id":"TGU0.ts","timestamp":1649752086702},{"id":"WxmZ.ts","timestamp":1649752179070},{"id":"S94m.ts","timestamp":1649752234333},{"id":"fvIz.ts","timestamp":1649752534349},{"id":"vXCI.ts","timestamp":1649752578221},{"id":"Y4pZ.ts","timestamp":1649752590237},{"id":"hEIO.ts","timestamp":1649752616633},{"id":"ajrZ.ts","timestamp":1649752646369},{"id":"lcZ0.ts","timestamp":1649752662785},{"id":"7KSL.ts","timestamp":1649752742988},{"id":"Q2xg.ts","timestamp":1649752953190},{"id":"MPda.ts","timestamp":1649753215251},{"id":"XKUk.ts","timestamp":1649753281151},{"id":"TOVY.ts","timestamp":1649753315606},{"id":"iigA.ts","timestamp":1649753342480},{"id":"osI3.ts","timestamp":1649753389213},{"id":"A6rg.ts","timestamp":1649753455383},{"id":"yJqt.ts","timestamp":1649753502223},{"id":"1iJI.ts","timestamp":1649753634341},{"id":"ZoxP.ts","timestamp":1649753754225},{"id":"V7NQ.ts","timestamp":1649753815293},{"id":"SiJO.ts","timestamp":1649753830413},{"id":"ieq9.ts","timestamp":1649753847751}]}