{"version":1,"resource":"file:///Users/shiyun/workspace/sirius_FE/src/pages/desktop/Project/Detail/Header.tsx","entries":[{"id":"jMsq.tsx","timestamp":1677398426255},{"id":"uMnY.tsx","timestamp":1677398502785},{"id":"dfhH.tsx","timestamp":1677398516947},{"id":"jqox.tsx","timestamp":1677398561988},{"id":"qwsJ.tsx","timestamp":1677398673277},{"id":"c5oi.tsx","timestamp":1677401943209},{"id":"U8tR.tsx","timestamp":1677559242719},{"id":"eYe6.tsx","timestamp":1677559265606},{"id":"ebvf.tsx","timestamp":1679539699820},{"id":"NKKr.tsx","timestamp":1679539875785},{"id":"7mBu.tsx","timestamp":1679539887277},{"id":"sIRY.tsx","timestamp":1679539909777},{"id":"PEI0.tsx","timestamp":1679539931511},{"id":"8o7S.tsx","timestamp":1679638609011},{"id":"6UuI.tsx","timestamp":1683783889452},{"id":"02f7.tsx","timestamp":1683783919351},{"id":"h60H.tsx","timestamp":1683783931494},{"id":"iCx9.tsx","timestamp":1683783967427},{"id":"1472.tsx","timestamp":1684230816266},{"id":"vDuH.tsx","timestamp":1684230863302}]}