{"version":1,"resource":"file:///Users/shiyun/workspace/sirius_FE/src/components/Dashboard/StrategyCards/Balance.tsx","entries":[{"id":"wllf.tsx","timestamp":1675762677723},{"id":"YXUy.tsx","source":"searchReplace.source","timestamp":1675840735346},{"id":"mKhK.tsx","timestamp":1675841133335},{"id":"vnqY.tsx","source":"searchReplace.source","timestamp":1675841986531},{"id":"GnXy.tsx","timestamp":1676344201359},{"id":"9bPs.tsx","source":"searchReplace.source","timestamp":1676358514149},{"id":"etNQ.tsx","source":"searchReplace.source","timestamp":1676358551677}]}