{"version":1,"resource":"file:///Users/shiyun/workspace/bond_trade/src/components/Slider/slider.less","entries":[{"id":"s6ld.less","timestamp":1654580811524},{"id":"4G0v.less","timestamp":1654580859691},{"id":"0ewK.less","timestamp":1654580936803},{"id":"MceP.less","timestamp":1654580961712},{"id":"F7QU.less","timestamp":1654581066597},{"id":"LAe7.less","timestamp":1654581159984},{"id":"PUUz.less","timestamp":1654581204328},{"id":"7G9T.less","timestamp":1654581270501},{"id":"s4EF.less","timestamp":1654581283625},{"id":"b8f9.less","timestamp":1654581308856},{"id":"UyQQ.less","timestamp":1654581326798},{"id":"DGmA.less","timestamp":1654581366743},{"id":"yCTU.less","timestamp":1654581381223},{"id":"F0dT.less","timestamp":1654581427781},{"id":"4lDu.less","timestamp":1655968391988},{"id":"BWBj.less","timestamp":1655971005972},{"id":"cdBP.less","timestamp":1657071975705}]}