{"version":1,"resource":"file:///Users/shiyun/workspace/sirius_FE/src/pages/desktop/ReportManage/index.tsx","entries":[{"id":"rQrd.tsx","timestamp":1686209407326},{"id":"2mP9.tsx","timestamp":1686731745605},{"id":"aF5B.tsx","timestamp":1686731770957},{"id":"FnrJ.tsx","timestamp":1686731910108},{"id":"G4vP.tsx","timestamp":1686731933675},{"id":"p0uI.tsx","timestamp":1686732028496},{"id":"bdIs.tsx","timestamp":1686732057287},{"id":"CjHm.tsx","timestamp":1686732072329},{"id":"la45.tsx","timestamp":1686732173977},{"id":"MVNJ.tsx","timestamp":1686807140652},{"id":"7rgf.tsx","timestamp":1687164870233},{"id":"P7y3.tsx","timestamp":1687165060317},{"id":"owpe.tsx","timestamp":1687165245609},{"id":"HuCK.tsx","timestamp":1687165389828},{"id":"aFp7.tsx","timestamp":1687165432262},{"id":"dXRr.tsx","timestamp":1687165464610},{"id":"OZl7.tsx","timestamp":1687165511433},{"id":"Q63I.tsx","timestamp":1687335546896},{"id":"9BvW.tsx","timestamp":1687336261997},{"id":"Z6uE.tsx","timestamp":1687336421404},{"id":"UHkF.tsx","timestamp":1687336646866},{"id":"XQmD.tsx","timestamp":1687336717703},{"id":"hSku.tsx","timestamp":1687336740442},{"id":"nsgh.tsx","timestamp":1687336789800},{"id":"73yQ.tsx","timestamp":1687336811799},{"id":"G5Un.tsx","timestamp":1687336867941},{"id":"i7H4.tsx","timestamp":1687336945730},{"id":"6riI.tsx","timestamp":1687337041459},{"id":"lU3B.tsx","timestamp":1687337060509},{"id":"8XQu.tsx","timestamp":1687337147190},{"id":"A3Lr.tsx","timestamp":1687337188832},{"id":"aRP4.tsx","timestamp":1687337281255},{"id":"9mA9.tsx","timestamp":1687337315642},{"id":"Oacg.tsx","timestamp":1687337365861},{"id":"Ib4P.tsx","timestamp":1687337383485},{"id":"ZPf2.tsx","timestamp":1687337403760},{"id":"6PJ1.tsx","timestamp":1687337488713},{"id":"xyWG.tsx","timestamp":1687337517373},{"id":"6qtr.tsx","timestamp":1687337568041},{"id":"0U99.tsx","timestamp":1687337630624},{"id":"Cd50.tsx","timestamp":1687337652271},{"id":"0eR7.tsx","source":"undoRedo.source","timestamp":1687337653783},{"id":"nRXd.tsx","timestamp":1687337673849},{"id":"S42E.tsx","timestamp":1687337695420},{"id":"THgj.tsx","timestamp":1687337746368},{"id":"yBsq.tsx","timestamp":1687337794315},{"id":"xVHh.tsx","timestamp":1687337812954},{"id":"NwsO.tsx","timestamp":1687338042506},{"id":"cmWG.tsx","timestamp":1687338257283},{"id":"Vu3G.tsx","timestamp":1687338703778}]}