{"version":1,"resource":"file:///Users/shiyun/workspace/sirius_FE/src/pages/m/GlobalSearch/index.tsx","entries":[{"id":"rQNL.tsx","timestamp":1674976803038},{"id":"5qoN.tsx","timestamp":1674977028561},{"id":"s7Qb.tsx","timestamp":1674977048208},{"id":"naX1.tsx","source":"moved.source","timestamp":1674977295330},{"id":"HdEL.tsx","timestamp":1674977410783},{"id":"RwC1.tsx","timestamp":1674977690743},{"id":"uDCN.tsx","timestamp":1674977807837},{"id":"tZuo.tsx","timestamp":1674977850136},{"id":"udUK.tsx","timestamp":1674977903316},{"id":"kPUs.tsx","timestamp":1674977914194},{"id":"pK5v.tsx","timestamp":1674978025447},{"id":"PXvY.tsx","timestamp":1674978061552},{"id":"wGZF.tsx","timestamp":1674978098111},{"id":"8SjV.tsx","timestamp":1674978141139},{"id":"31Kb.tsx","timestamp":1674978204370},{"id":"7iEa.tsx","timestamp":1674978239561},{"id":"1BvS.tsx","timestamp":1675151363255},{"id":"5VcL.tsx","timestamp":1675851721180},{"id":"1aht.tsx","timestamp":1675851748847},{"id":"cJ1H.tsx","timestamp":1676942563137}]}