{"version":1,"resource":"file:///Users/shiyun/workspace/basic_framework/src/components/Header/Header.tsx","entries":[{"id":"Luz9.tsx","timestamp":1667649878131},{"id":"J2pL.tsx","timestamp":1667783304275},{"id":"1Aob.tsx","timestamp":1669343221170},{"id":"6zZo.tsx","timestamp":1669343275175},{"id":"GbDi.tsx","timestamp":1669355210725},{"id":"mZfw.tsx","timestamp":1669624545357},{"id":"edZH.tsx","timestamp":1669624650804},{"id":"ZPvZ.tsx","timestamp":1669624662692},{"id":"pWXU.tsx","timestamp":1669625507430},{"id":"TmfI.tsx","timestamp":1669625554641},{"id":"DM0b.tsx","timestamp":1669625564883},{"id":"NyVU.tsx","timestamp":1669625628421},{"id":"5uT2.tsx","timestamp":1669625662622},{"id":"ZkyQ.tsx","timestamp":1669626034397},{"id":"no8D.tsx","timestamp":1669626057196},{"id":"nKXs.tsx","timestamp":1669626463152},{"id":"YMhK.tsx","timestamp":1669626670185},{"id":"eDj7.tsx","timestamp":1669626752453},{"id":"eiKj.tsx","timestamp":1669627137601},{"id":"ecah.tsx","timestamp":1669627255806},{"id":"oJTQ.tsx","timestamp":1669627689601},{"id":"eK9w.tsx","timestamp":1669627725686},{"id":"yr3y.tsx","timestamp":1669627926122},{"id":"TX6J.tsx","timestamp":1669627993087},{"id":"CgNq.tsx","timestamp":1669628211707},{"id":"KxU1.tsx","timestamp":1669796897740},{"id":"5pax.tsx","timestamp":1669796933274},{"id":"cYXC.tsx","timestamp":1669796943608},{"id":"M5H9.tsx","timestamp":1669797026577},{"id":"QKcN.tsx","timestamp":1669797055080},{"id":"MQJM.tsx","timestamp":1669797094663},{"id":"FFtt.tsx","timestamp":1669802140166},{"id":"cFhk.tsx","timestamp":1669856056187},{"id":"pRKh.tsx","timestamp":1669859781185},{"id":"v3jR.tsx","timestamp":1670393378902},{"id":"VAhS.tsx","timestamp":1670395183286},{"id":"EcdT.tsx","source":"undoRedo.source","timestamp":1670395539836},{"id":"yLa2.tsx","timestamp":1670400537741},{"id":"xjhy.tsx","timestamp":1670400603542},{"id":"3YTh.tsx","source":"undoRedo.source","timestamp":1670401615807},{"id":"3YsP.tsx","timestamp":1670401619171},{"id":"wVJD.tsx","timestamp":1670401704664},{"id":"o3Jx.tsx","timestamp":1670401798262},{"id":"cSou.tsx","timestamp":1670401816189},{"id":"zVph.tsx","timestamp":1670811455269},{"id":"g2hL.tsx","source":"undoRedo.source","timestamp":1670811461592},{"id":"GX5t.tsx","timestamp":1670811471621},{"id":"MV31.tsx","timestamp":1670820240752},{"id":"dW9a.tsx","timestamp":1670820325994},{"id":"TAtX.tsx","timestamp":1670896565701}]}